astred/__init__.py
astred/aligned.py
astred/aligner.py
astred/base.py
astred/enum.py
astred/pairs.py
astred/sentence.py
astred/span.py
astred/tree.py
astred/utils.py
astred/word.py
astred-0.9.7.dist-info/LICENSE
astred-0.9.7.dist-info/METADATA
astred-0.9.7.dist-info/WHEEL
astred-0.9.7.dist-info/top_level.txt
astred-0.9.7.dist-info/RECORD
