Metadata-Version: 2.1
Name: astred
Version: 0.9.7
Summary: A collection of syntactic metrics to calculate (dis)similarities between source and target sentences.
Home-page: https://github.com/BramVanroy/astred
Author: Bram Vanroy
Author-email: bramvanroy@hotmail.com
License: Apache 2.0
Project-URL: Issue tracker, https://github.com/BramVanroy/astred/issues
Project-URL: Source, https://github.com/BramVanroy/astred
Keywords: nlp tree-edit-distance ted syntax compling computational-linguistics syntactic-distance translation
Platform: UNKNOWN
Classifier: Development Status :: 4 - Beta
Classifier: Intended Audience :: Developers
Classifier: Intended Audience :: Science/Research
Classifier: Topic :: Scientific/Engineering
Classifier: Topic :: Text Processing
Classifier: Programming Language :: Python :: 3.7
Classifier: Programming Language :: Python :: 3.8
Classifier: Programming Language :: Python :: 3.9
Classifier: Operating System :: OS Independent
Requires-Python: >=3.7
Requires-Dist: apted
Requires-Dist: nltk
Provides-Extra: all
Requires-Dist: stanza ; extra == 'all'
Requires-Dist: spacy (>=3.0) ; extra == 'all'
Provides-Extra: dev
Requires-Dist: stanza ; extra == 'dev'
Requires-Dist: spacy (>=3.0) ; extra == 'dev'
Requires-Dist: isort (>=5.5.4) ; extra == 'dev'
Requires-Dist: black ; extra == 'dev'
Requires-Dist: flake8 ; extra == 'dev'
Requires-Dist: pytest ; extra == 'dev'
Requires-Dist: pytest-cases ; extra == 'dev'
Requires-Dist: pygments ; extra == 'dev'
Provides-Extra: parsers
Requires-Dist: stanza ; extra == 'parsers'
Requires-Dist: spacy (>=3.0) ; extra == 'parsers'
Provides-Extra: spacy
Requires-Dist: spacy (>=3.0) ; extra == 'spacy'
Provides-Extra: stanza
Requires-Dist: stanza ; extra == 'stanza'
